iris/__init__.py
iris/config.yaml
iris/main.py
iris/gradio/__init__.py
iris/gradio/run.py
iris/sdk/__init__.py
iris/sdk/conf_manager.py
iris/sdk/exception.py
iris/sdk/iris_sdk.py
iris/sdk/safe_convert.py
iris/sdk/utils/auth_utils.py
iris/sdk/utils/display_utils.py
iris/sdk/utils/docker_utils.py
iris/sdk/utils/io_utils.py
iris/sdk/utils/machine_utils.py
iris/sdk/utils/telemetry_utils.py
iris/sdk/utils/utils.py
iris/sdk/utils/validation_utils.py
titan_iris-0.58.2.dist-info/METADATA
titan_iris-0.58.2.dist-info/WHEEL
titan_iris-0.58.2.dist-info/entry_points.txt
titan_iris-0.58.2.dist-info/top_level.txt
titan_iris-0.58.2.dist-info/RECORD
