Metadata-Version: 2.1
Name: titan-iris
Version: 0.58.2
Requires-Dist: typer ~=0.7.0
Requires-Dist: rich ~=13.3.1
Requires-Dist: omegaconf ~=2.3.0
Requires-Dist: requests ~=2.28.2
Requires-Dist: auth0-python ~=3.24.1
Requires-Dist: python-dotenv ~=0.19.1
Requires-Dist: docker ~=6.0.1
Requires-Dist: tqdm ~=4.64.1
Requires-Dist: wget ~=3.2
Requires-Dist: jmespath ~=1.0
Requires-Dist: tritonclient[http] ~=2.30.0
Requires-Dist: numpy >=1.20.0
Requires-Dist: tabulate ~=0.9.0
Requires-Dist: trogon ~=0.2.1
Requires-Dist: shortuuid ~=1.0.11
Requires-Dist: einops ~=0.6.1
Requires-Dist: py-cpuinfo ~=8.0.0
Requires-Dist: importlib-metadata >=4.0.1
Requires-Dist: pandas >=1.3.5
